MANIFEST.in
README.rst
setup.cfg
setup.py
pythiacrypto/__init__.py
pythiacrypto/blsgroup.py
pythiacrypto/blspop.py
pythiacrypto/common.py
pythiacrypto/ecgroup.py
pythiacrypto/ecoprf.py
pythiacrypto/groups.py
pythiacrypto/primeorder.py
pythiacrypto/profileClient.py
pythiacrypto/taggedPrf.py
pythiacrypto/testPerformance.py
pythiacrypto/testPrf.py
pythiacrypto/tweakablePrf.py
pythiacrypto.egg-info/PKG-INFO
pythiacrypto.egg-info/SOURCES.txt
pythiacrypto.egg-info/dependency_links.txt
pythiacrypto.egg-info/not-zip-safe
pythiacrypto.egg-info/top_level.txt