Metadata-Version: 1.1
Name: pythiacrypto
Version: 1.0
Summary: Enables both client-side and server-side password hardening using a remote cryptographic server that provides an unpdateable, verifiable, and secure psuedorandom function (PRF) service. NOTE: Pythia requires the Charm Crypto library for Python http://www.charm-crypto.com/Download.html but there isn't a PIP package yet in existence.
Home-page: https://pages.cs.wisc.edu/~ace/projects/pythia.html
Author: Adam Everspaugh
Author-email: ace@cs.wisc.edu
License: MIT
Platform: UNKNOWN
Classifier: Development Status :: 4 - Beta
Classifier: Environment :: Console
Classifier: Intended Audience :: Developers
Classifier: Intended Audience :: Information Technology
Classifier: License :: OSI Approved :: MIT License
Classifier: Operating System :: MacOS
Classifier: Operating System :: MacOS :: MacOS X
Classifier: Operating System :: POSIX :: Linux
Classifier: Operating System :: Unix
Classifier: Programming Language :: Python :: 2
Classifier: Programming Language :: Python :: 2.7
Classifier: Topic :: Security
Classifier: Topic :: Security :: Cryptography
